mir_bootleg_score/__init__.py
mir_bootleg_score/extractBootlegFeatures.py
mir_bootleg_score-0.1.0.dist-info/LICENSE
mir_bootleg_score-0.1.0.dist-info/METADATA
mir_bootleg_score-0.1.0.dist-info/WHEEL
mir_bootleg_score-0.1.0.dist-info/top_level.txt
mir_bootleg_score-0.1.0.dist-info/RECORD
