Metadata-Version: 2.1
Name: mir-bootleg-score
Version: 0.1.0
Summary: Built for MIR Lab. Tools for converting png images into bootleg score features.
Home-page: https://github.com/shuds13/pyexample
Author: Arjun Taneja
Author-email: ataneja@g.hmc.edu
License: BSD 2-clause
Platform: UNKNOWN
Classifier: Development Status :: 1 - Planning
Classifier: Intended Audience :: Science/Research
Classifier: License :: OSI Approved :: BSD License
Classifier: Operating System :: POSIX :: Linux
Classifier: Programming Language :: Python :: 2
Classifier: Programming Language :: Python :: 2.7
Classifier: Programming Language :: Python :: 3
Classifier: Programming Language :: Python :: 3.10
Requires-Dist: Pillow
Requires-Dist: librosa
Requires-Dist: matplotlib
Requires-Dist: multiprocess
Requires-Dist: numpy
Requires-Dist: opencv-python
Requires-Dist: scikit-image
Requires-Dist: scikit-learn
Requires-Dist: scipy
